Workbook

Sheet Inputs
C3: Refresh Grant Model — Inputs
C5: Management inputs and approved policy multipliers
C6: (USD, shares/units, months and multiples as labeled)
C8: Individual and plan inputs — enter approved data in blue cells
C9: Input | D9: Value | E9: Definition / Source
C10: Annual target equity value for role (TEV) | E10: Board-approved annual target equity value for the employee's role/level.
C11: Target coverage months (CM) | E11: Months of future unvested-equity coverage targeted by policy.
C12: Fair market value per share / unit (FMV) | E12: Confirmed fair market value per share/unit; do not use enterprise value.
C13: Current unvested options / units (UO) | E13: Granted and unvested options/units held by the employee.
C14: Individual grant cap (IC) | E14: Maximum refresh shares/units permitted for one employee in this cycle.
C15: Remaining ESOP pool capacity (PC) | E15: Unallocated shares/units still available in the ESOP pool.
C16: Basic shares / units outstanding | E16: Basic shares/units outstanding before the proposed refresh grant.
C19: Policy multipliers — initial values are proposed policy settings; Board approval required
C20: Multiplier | D20: Proposed value | E20: Use case
C21: Performance factor — outstanding | D21: 1.25 | E21: Use only after calibrated annual performance review.
C22: Performance factor — strong | D22: 1 | E22: Standard high-performance outcome.
C23: Performance factor — meets expectations | D23: 0.75 | E23: Minimum retention coverage subject to role needs.
C24: Performance factor — needs improvement | D24: 0 | E24: No automatic refresh grant; exception needs committee approval.
C25: Criticality factor — critical role | D25: 1.2 | E25: Security, core AI, architecture or hard-to-replace role.
C26: Criticality factor — standard role | D26: 1 | E26: Default role-criticality setting.
C27: Criticality factor — lower urgency | D27: 0.85 | E27: Use only with documented business rationale.
C28: Retention risk factor — documented high risk | D28: 1.15 | E28: Stay interview and mitigation plan required.
C29: Retention risk factor — normal | D29: 1 | E29: Default risk setting.
C30: Retention risk factor — low | D30: 0.9 | E30: Use for budget prioritization; not a punitive factor.
C33: مدل فقط پس از ورود داده‌های تاییدشده خروجی عددی ایجاد می‌کند.
C34: All blue-font cells are hardcoded inputs or policy parameters and include audit comments.

Sheet Model
C3: Refresh Grant Model — Calculation
C5: Formula-driven calculation; cross-sheet references are displayed in green
C6: (USD, shares/units and multiples as labeled)
C8: Linked inputs
C10: Annual target equity value (TEV) | D10: =Inputs!D10
C11: Target coverage months (CM) | D11: =Inputs!D11
C12: Fair market value per share / unit (FMV) | D12: =Inputs!D12
C13: Current unvested options / units (UO) | D13: =Inputs!D13
C14: Individual grant cap (IC) | D14: =Inputs!D14
C15: Remaining ESOP pool capacity (PC) | D15: =Inputs!D15
C16: Basic shares / units outstanding | D16: =Inputs!D16
C19: Selected multipliers — set by committee after calibration
C20: Performance factor (PF) | D20: =IFERROR(INDEX(Inputs!$D$21:$D$24,MATCH(E20,Inputs!$C$21:$C$24,0)),"") | E20: Performance factor — strong
C21: Criticality factor (CF) | D21: =IFERROR(INDEX(Inputs!$D$25:$D$27,MATCH(E21,Inputs!$C$25:$C$27,0)),"") | E21: Criticality factor — standard role
C22: Retention risk factor (RF) | D22: =IFERROR(INDEX(Inputs!$D$28:$D$30,MATCH(E22,Inputs!$C$28:$C$30,0)),"") | E22: Retention risk factor — normal
C25: Refresh Grant calculation
C26: Target outstanding value (TOV) | D26: =IF(OR(NOT(ISNUMBER(D10)),NOT(ISNUMBER(D11))),"",D10*(D11/12))
C27: Current unvested reference value (CURV) | D27: =IF(OR(NOT(ISNUMBER(D12)),NOT(ISNUMBER(D13))),"",D12*D13)
C28: Pre-adjustment retention gap (PARG) | D28: =IF(OR(NOT(ISNUMBER(D26)),NOT(ISNUMBER(D27))),"",MAX(D26-D27,0))
C29: Gross refresh shares / units (GRS) | D29: =IF(OR(NOT(ISNUMBER(D28)),NOT(ISNUMBER(D12)),D12<=0,NOT(ISNUMBER(D20)),NOT(ISNUMBER(D21)),NOT(ISNUMBER(D22))),"",(D28/D12)*D20*D21*D22)
C30: Recommended refresh grant (RRG) | D30: =IF(OR(NOT(ISNUMBER(D29)),NOT(ISNUMBER(D14)),NOT(ISNUMBER(D15))),"",MIN(D29,D14,D15))
C31: Reference value of recommended grant | D31: =IF(OR(NOT(ISNUMBER(D30)),NOT(ISNUMBER(D12))),"",D30*D12)
C32: Implied basic-share dilution | D32: =IF(OR(NOT(ISNUMBER(D30)),NOT(ISNUMBER(D16)),D16<=0),"",D30/D16)
C33: Capacity remaining after recommendation | D33: =IF(OR(NOT(ISNUMBER(D15)),NOT(ISNUMBER(D30))),"",D15-D30)
C34: Review status | D34: =IF(OR(NOT(ISNUMBER(D12)),D12<=0,NOT(ISNUMBER(D14)),NOT(ISNUMBER(D15))),"INPUTS REQUIRED",IF(D30>D15,"POOL CAP BREACH",IF(D30>D14,"INDIVIDUAL CAP BREACH","READY FOR COMMITTEE REVIEW")))
C37: مدل فقط پس از ورود داده‌های تاییدشده خروجی عددی ایجاد می‌کند.
C38: Formula logic: RRG = MIN(((MAX((TEV × CM/12) − (UO × FMV), 0) / FMV) × PF × CF × RF), IC, PC).

Sheet Board Summary
C3: Refresh Grant — Board Summary
C5: Aggregate control view for Compensation Committee and Board
C6: (Template; no employee data is pre-populated)
C8: Cycle-level controls
C9: Metric | D9: Formula / result | E9: Board interpretation
C10: Proposed refresh shares / units | D10: =Model!D30 | E10: Single-employee output; aggregate separately for batch awards.
C11: Reference value of grant | D11: =Model!D31 | E11: Reference value based on current FMV; not a promise of future value.
C12: ESOP pool capacity before grant | D12: =Inputs!D15 | E12: Confirm against cap table immediately before Board approval.
C13: ESOP pool capacity after grant | D13: =Model!D33 | E13: Must remain non-negative; Board approval required for any pool expansion.
C14: Implied basic-share dilution | D14: =Model!D32 | E14: Review alongside fully diluted cap-table analysis.
C15: Decision status | D15: =Model!D34 | E15: Do not issue any grant if status is not READY FOR COMMITTEE REVIEW.
C19: Committee checklist
C20: 1. Confirm latest FMV and cap-table capacity as-of the Board decision date.
C21: 2. Confirm performance, role criticality and retention-risk selections have evidence and calibration notes.
C22: 3. Confirm the grant is within the individual cap and the approved ESOP pool.
C23: 4. Confirm legal documentation, vesting terms, strike price and tax treatment with counsel.
C24: 5. Record the formal committee decision, conflicts of interest and grant communication owner.
C27: مدل فقط پس از ورود داده‌های تاییدشده خروجی عددی ایجاد می‌کند.
C28: This template does not replace a fully diluted cap-table, valuation opinion, tax review or Board resolution.
